Workbook
Name aporte: Investimentos!$D$15
Name patrimonio: Investimentos!$D$18
Name qtd_anos: Investimentos!$D$16
Name rendimento_carteira: Investimentos!$D$11
Name salario: Investimentos!$D$10
Name sugestao_investimento: Investimentos!$D$12
Name taxa_mensal: Investimentos!$D$17

Sheet Investimentos
B9: CONFIGURAÇÕES
B10: Salário | D10: 2000
B11: Rendimento da Carteira | D11: 0.006
B12: Sugestão de Investimento | D12: =D10*30% -> 600
B14: INVESTIMENTO MENSAL
B15: Quanto investir por mês? | D15: 200
B16: Por quantos anos? | D16: 10
B17: Taxa de Rendimento mensal? | D17: 0.01079
B18: Patrimônio acumulado? | D18: =FV(taxa_mensal,qtd_anos*12,-aporte) -> 48656.843
B19: Dividendos mensais? | D19: =patrimonio*rendimento_carteira -> 291.94106
B21: CENÁRIOS
C22: Acumulado | D22: Dividendos
A23: 2 | B23: Quanto em 2 anos? | C23: =FV($D$17,$A23*12,-$D$15) -> 5445.5255 | D23: =C23*rendimento_carteira -> 32.673153
A24: 5 | B24: Quanto em 5 anos? | C24: =FV($D$17,$A24*12,-$D$15) -> 16755.383 | D24: =C24*rendimento_carteira -> 100.5323
A25: 10 | B25: Quanto em 10 anos? | C25: =FV($D$17,$A25*12,-$D$15) -> 48656.843 | D25: =C25*rendimento_carteira -> 291.94106
A26: 20 | B26: Quanto em 20 anos? | C26: =FV($D$17,$A26*12,-$D$15) -> 225039.68 | D26: =C26*rendimento_carteira -> 1350.2381
A27: 30 | B27: Quanto em 30 anos? | C27: =FV($D$17,$A27*12,-$D$15) -> 864433.93 | D27: =C27*rendimento_carteira -> 5186.6036
B30: PERFIL | C30: Conservador
B31: Valor investido por mês | C31: =aporte -> 200
B33: TIPOS DE FII | C33: % Sugerido | D33: Valores
B34: Papel | C34: =VLOOKUP($C$30&"-"&B34,Apoio!$B:$E,4,FALSE) -> 0.3 | D34: =C34*$C$31 -> 60
B35: Tijolo | C35: =VLOOKUP($C$30&"-"&B35,Apoio!$B:$E,4,FALSE) -> 0.5 | D35: =C35*$C$31 -> 100
B36: Híbridos | C36: =VLOOKUP($C$30&"-"&B36,Apoio!$B:$E,4,FALSE) -> 0.1 | D36: =C36*$C$31 -> 20
B37: FOF | C37: =VLOOKUP($C$30&"-"&B37,Apoio!$B:$E,4,FALSE) -> 0.1 | D37: =C37*$C$31 -> 20
B38: Desenvolvimento | C38: =VLOOKUP($C$30&"-"&B38,Apoio!$B:$E,4,FALSE) -> 0 | D38: =C38*$C$31 -> 0
B39: Hotelarias | C39: =VLOOKUP($C$30&"-"&B39,Apoio!$B:$E,4,FALSE) -> 0 | D39: =C39*$C$31 -> 0
D40: =SUM(D34:D39) -> 200

Sheet Apoio
B2: CHAVE COMPOSTA | C2: PERFIL | D2: TIPO DE FII | E2: %
B3: =C3&"-"&D3 -> Conservador-Papel | C3: Conservador | D3: Papel | E3: 0.3
B4: =C4&"-"&D4 -> Conservador-Tijolo | C4: Conservador | D4: Tijolo | E4: 0.5
B5: =C5&"-"&D5 -> Conservador-Híbridos | C5: Conservador | D5: Híbridos | E5: 0.1
B6: =C6&"-"&D6 -> Conservador-FOF | C6: Conservador | D6: FOF | E6: 0.1
B7: =C7&"-"&D7 -> Conservador-Desenvolvimento | C7: Conservador | D7: Desenvolvimento | E7: 0
B8: =C8&"-"&D8 -> Conservador-Hotelarias | C8: Conservador | D8: Hotelarias | E8: 0
B9: =C9&"-"&D9 -> Moderado-Papel | C9: Moderado | D9: Papel | E9: 0.32
B10: =C10&"-"&D10 -> Moderado-Tijolo | C10: Moderado | D10: Tijolo | E10: 0.35
B11: =C11&"-"&D11 -> Moderado-Híbridos | C11: Moderado | D11: Híbridos | E11: 0.08
B12: =C12&"-"&D12 -> Moderado-FOF | C12: Moderado | D12: FOF | E12: 0.05
B13: =C13&"-"&D13 -> Moderado-Desenvolvimento | C13: Moderado | D13: Desenvolvimento | E13: 0.1
B14: =C14&"-"&D14 -> Moderado-Hotelarias | C14: Moderado | D14: Hotelarias | E14: 0.1
... B20: =C20&"-"&D20 -> Agressivo-Hotelarias | C20: Agressivo | D20: Hotelarias | E20: 0.1
